{
  "model_id": 4509,
  "brand": "지프",
  "name": "Wrangler",
  "img": "https://autoimg.danawa.com/photo/4509/model_360.png",
  "lineups": [
    {
      "lineupNo": 53678,
      "name": "2도어 가솔린 2.0",
      "year": "2026년형",
      "percent": 0,
      "trims": [
        {
          "trimNo": 94631,
          "trimName": "Rubicon 2 Door Hard Top",
          "price": 83900000,
          "transmission": "",
          "percent": 0,
          "options": [],
          "exteriorColors": [
            {
              "colorCode": "C11",
              "colorType": 1,
              "colorName": "Black Clear-Coat",
              "colorHexadecimal": "0e0a09",
              "rank": 0,
              "percent": 0,
              "bundle": "",
              "sAddOptionCode": ""
            },
            {
              "colorCode": "C12",
              "colorType": 1,
              "colorName": "Granite Crystal Metallic Clear-Coat",
              "colorHexadecimal": "313536",
              "rank": 0,
              "percent": 0,
              "bundle": "",
              "sAddOptionCode": ""
            },
            {
              "colorCode": "C13",
              "colorType": 1,
              "colorName": "Anvil Clear-Coat",
              "colorHexadecimal": "72858b",
              "rank": 0,
              "percent": 0,
              "bundle": "",
              "sAddOptionCode": ""
            },
            {
              "colorCode": "C14",
              "colorType": 1,
              "colorName": "Hydro Blue Pearl-Coat",
              "colorHexadecimal": "104577",
              "rank": 0,
              "percent": 0,
              "bundle": "",
              "sAddOptionCode": ""
            },
            {
              "colorCode": "C15",
              "colorType": 1,
              "colorName": "Firecracker Red Clear-Coat",
              "colorHexadecimal": "ce1302",
              "rank": 0,
              "percent": 0,
              "bundle": "",
              "sAddOptionCode": ""
            },
            {
              "colorCode": "C16",
              "colorType": 1,
              "colorName": "Bright White Clear-Coat",
              "colorHexadecimal": "ffffff",
              "rank": 0,
              "percent": 0,
              "bundle": "",
              "sAddOptionCode": ""
            }
          ],
          "interiorColors": []
        }
      ]
    },
    {
      "lineupNo": 53679,
      "name": "4도어 가솔린 2.0",
      "year": "2026년형",
      "percent": 23,
      "trims": [
        {
          "trimNo": 94632,
          "trimName": "Sport S 4 Door Hard Top",
          "price": 75700000,
          "transmission": "",
          "percent": 0,
          "options": [],
          "exteriorColors": [
            {
              "colorCode": "C11",
              "colorType": 1,
              "colorName": "Black Clear-Coat",
              "colorHexadecimal": "0e0a09",
              "rank": 0,
              "percent": 0,
              "bundle": "",
              "sAddOptionCode": ""
            },
            {
              "colorCode": "C12",
              "colorType": 1,
              "colorName": "Granite Crystal Metallic Clear-Coat",
              "colorHexadecimal": "313536",
              "rank": 0,
              "percent": 0,
              "bundle": "",
              "sAddOptionCode": ""
            },
            {
              "colorCode": "C13",
              "colorType": 1,
              "colorName": "Anvil Clear-Coat",
              "colorHexadecimal": "72858b",
              "rank": 0,
              "percent": 0,
              "bundle": "",
              "sAddOptionCode": ""
            },
            {
              "colorCode": "C14",
              "colorType": 1,
              "colorName": "Hydro Blue Pearl-Coat",
              "colorHexadecimal": "104577",
              "rank": 0,
              "percent": 0,
              "bundle": "",
              "sAddOptionCode": ""
            },
            {
              "colorCode": "C15",
              "colorType": 1,
              "colorName": "Firecracker Red Clear-Coat",
              "colorHexadecimal": "ce1302",
              "rank": 0,
              "percent": 0,
              "bundle": "",
              "sAddOptionCode": ""
            },
            {
              "colorCode": "C16",
              "colorType": 1,
              "colorName": "Bright White Clear-Coat",
              "colorHexadecimal": "ffffff",
              "rank": 0,
              "percent": 0,
              "bundle": "",
              "sAddOptionCode": ""
            }
          ],
          "interiorColors": []
        },
        {
          "trimNo": 94633,
          "trimName": "Sahara 4 Door Hard Top",
          "price": 84400000,
          "transmission": "",
          "percent": 60,
          "options": [],
          "exteriorColors": [
            {
              "colorCode": "C11",
              "colorType": 1,
              "colorName": "Black Clear-Coat",
              "colorHexadecimal": "0e0a09",
              "rank": 0,
              "percent": 0,
              "bundle": "",
              "sAddOptionCode": ""
            },
            {
              "colorCode": "C12",
              "colorType": 1,
              "colorName": "Granite Crystal Metallic Clear-Coat",
              "colorHexadecimal": "313536",
              "rank": 0,
              "percent": 0,
              "bundle": "",
              "sAddOptionCode": ""
            },
            {
              "colorCode": "C13",
              "colorType": 1,
              "colorName": "Anvil Clear-Coat",
              "colorHexadecimal": "72858b",
              "rank": 0,
              "percent": 0,
              "bundle": "",
              "sAddOptionCode": ""
            },
            {
              "colorCode": "C14",
              "colorType": 1,
              "colorName": "Hydro Blue Pearl-Coat",
              "colorHexadecimal": "104577",
              "rank": 0,
              "percent": 0,
              "bundle": "",
              "sAddOptionCode": ""
            },
            {
              "colorCode": "C15",
              "colorType": 1,
              "colorName": "Firecracker Red Clear-Coat",
              "colorHexadecimal": "ce1302",
              "rank": 0,
              "percent": 0,
              "bundle": "",
              "sAddOptionCode": ""
            },
            {
              "colorCode": "C16",
              "colorType": 1,
              "colorName": "Bright White Clear-Coat",
              "colorHexadecimal": "ffffff",
              "rank": 0,
              "percent": 0,
              "bundle": "",
              "sAddOptionCode": ""
            }
          ],
          "interiorColors": []
        },
        {
          "trimNo": 94634,
          "trimName": "Sahara 4 Door Power Top",
          "price": 87400000,
          "transmission": "",
          "percent": 20,
          "options": [],
          "exteriorColors": [
            {
              "colorCode": "C11",
              "colorType": 1,
              "colorName": "Black Clear-Coat",
              "colorHexadecimal": "0e0a09",
              "rank": 0,
              "percent": 0,
              "bundle": "",
              "sAddOptionCode": ""
            },
            {
              "colorCode": "C12",
              "colorType": 1,
              "colorName": "Granite Crystal Metallic Clear-Coat",
              "colorHexadecimal": "313536",
              "rank": 0,
              "percent": 0,
              "bundle": "",
              "sAddOptionCode": ""
            },
            {
              "colorCode": "C13",
              "colorType": 1,
              "colorName": "Anvil Clear-Coat",
              "colorHexadecimal": "72858b",
              "rank": 0,
              "percent": 0,
              "bundle": "",
              "sAddOptionCode": ""
            },
            {
              "colorCode": "C14",
              "colorType": 1,
              "colorName": "Hydro Blue Pearl-Coat",
              "colorHexadecimal": "104577",
              "rank": 0,
              "percent": 0,
              "bundle": "",
              "sAddOptionCode": ""
            },
            {
              "colorCode": "C15",
              "colorType": 1,
              "colorName": "Firecracker Red Clear-Coat",
              "colorHexadecimal": "ce1302",
              "rank": 0,
              "percent": 0,
              "bundle": "",
              "sAddOptionCode": ""
            },
            {
              "colorCode": "C16",
              "colorType": 1,
              "colorName": "Bright White Clear-Coat",
              "colorHexadecimal": "ffffff",
              "rank": 0,
              "percent": 0,
              "bundle": "",
              "sAddOptionCode": ""
            }
          ],
          "interiorColors": []
        },
        {
          "trimNo": 94635,
          "trimName": "Rubicon 4 Door Hard Top",
          "price": 86900000,
          "transmission": "",
          "percent": 10,
          "options": [],
          "exteriorColors": [
            {
              "colorCode": "C11",
              "colorType": 1,
              "colorName": "Black Clear-Coat",
              "colorHexadecimal": "0e0a09",
              "rank": 0,
              "percent": 0,
              "bundle": "",
              "sAddOptionCode": ""
            },
            {
              "colorCode": "C12",
              "colorType": 1,
              "colorName": "Granite Crystal Metallic Clear-Coat",
              "colorHexadecimal": "313536",
              "rank": 0,
              "percent": 0,
              "bundle": "",
              "sAddOptionCode": ""
            },
            {
              "colorCode": "C13",
              "colorType": 1,
              "colorName": "Anvil Clear-Coat",
              "colorHexadecimal": "72858b",
              "rank": 0,
              "percent": 0,
              "bundle": "",
              "sAddOptionCode": ""
            },
            {
              "colorCode": "C14",
              "colorType": 1,
              "colorName": "Hydro Blue Pearl-Coat",
              "colorHexadecimal": "104577",
              "rank": 0,
              "percent": 0,
              "bundle": "",
              "sAddOptionCode": ""
            },
            {
              "colorCode": "C15",
              "colorType": 1,
              "colorName": "Firecracker Red Clear-Coat",
              "colorHexadecimal": "ce1302",
              "rank": 0,
              "percent": 0,
              "bundle": "",
              "sAddOptionCode": ""
            },
            {
              "colorCode": "C16",
              "colorType": 1,
              "colorName": "Bright White Clear-Coat",
              "colorHexadecimal": "ffffff",
              "rank": 0,
              "percent": 0,
              "bundle": "",
              "sAddOptionCode": ""
            }
          ],
          "interiorColors": []
        },
        {
          "trimNo": 94636,
          "trimName": "Rubicon 4 Door Power Top",
          "price": 89900000,
          "transmission": "",
          "percent": 0,
          "options": [],
          "exteriorColors": [
            {
              "colorCode": "C11",
              "colorType": 1,
              "colorName": "Black Clear-Coat",
              "colorHexadecimal": "0e0a09",
              "rank": 0,
              "percent": 0,
              "bundle": "",
              "sAddOptionCode": ""
            },
            {
              "colorCode": "C12",
              "colorType": 1,
              "colorName": "Granite Crystal Metallic Clear-Coat",
              "colorHexadecimal": "313536",
              "rank": 0,
              "percent": 0,
              "bundle": "",
              "sAddOptionCode": ""
            },
            {
              "colorCode": "C13",
              "colorType": 1,
              "colorName": "Anvil Clear-Coat",
              "colorHexadecimal": "72858b",
              "rank": 0,
              "percent": 0,
              "bundle": "",
              "sAddOptionCode": ""
            },
            {
              "colorCode": "C14",
              "colorType": 1,
              "colorName": "Hydro Blue Pearl-Coat",
              "colorHexadecimal": "104577",
              "rank": 0,
              "percent": 0,
              "bundle": "",
              "sAddOptionCode": ""
            },
            {
              "colorCode": "C15",
              "colorType": 1,
              "colorName": "Firecracker Red Clear-Coat",
              "colorHexadecimal": "ce1302",
              "rank": 0,
              "percent": 0,
              "bundle": "",
              "sAddOptionCode": ""
            },
            {
              "colorCode": "C16",
              "colorType": 1,
              "colorName": "Bright White Clear-Coat",
              "colorHexadecimal": "ffffff",
              "rank": 0,
              "percent": 0,
              "bundle": "",
              "sAddOptionCode": ""
            }
          ],
          "interiorColors": []
        }
      ]
    }
  ]
}