{
  "model_id": 4530,
  "brand": "애스턴마틴",
  "name": "DB12",
  "img": "https://autoimg.danawa.com/photo/4530/model_360.png",
  "lineups": [
    {
      "lineupNo": 52824,
      "name": "볼란테 가솔린 4.0",
      "year": "2026년형",
      "percent": 0,
      "trims": [
        {
          "trimNo": 91607,
          "trimName": "V8 Volante",
          "price": 365000000,
          "transmission": "",
          "percent": 0,
          "options": [],
          "exteriorColors": [],
          "interiorColors": []
        }
      ]
    },
    {
      "lineupNo": 50531,
      "name": "쿠페 가솔린 4.0",
      "year": "2024년형",
      "percent": 0,
      "trims": [
        {
          "trimNo": 82778,
          "trimName": "V8",
          "price": 309000000,
          "transmission": "",
          "percent": 0,
          "options": [],
          "exteriorColors": [],
          "interiorColors": []
        }
      ]
    }
  ]
}